<annotation>
	<folder>JPEGImages</folder>
	<filename>0048.jpg</filename>
	<path>E:\VSCode\make_voc\subset2_2\JPEGImages\0048.jpg</path>
	<source>
		<database>Unknown</database>
	</source>
	<size>
		<width>512</width>
		<height>512</height>
		<depth>1</depth>
	</size>
	<segmented>0</segmented>
	<object>
		<name>nodule</name>
		<pose>Unspecified</pose>
		<truncated>0</truncated>
		<difficult>0</difficult>
		<bndbox>
			<xmin>82</xmin>
			<ymin>188</ymin>
			<xmax>88</xmax>
			<ymax>194</ymax>
		</bndbox>
	</object>
	<object>
		<name>nodule</name>
		<pose>Unspecified</pose>
		<truncated>0</truncated>
		<difficult>0</difficult>
		<bndbox>
			<xmin>106</xmin>
			<ymin>114</ymin>
			<xmax>121</xmax>
			<ymax>127</ymax>
		</bndbox>
	</object>
</annotation>
